{"frames": {

"Sparkle0000":
{
	"frame": {"x":1,"y":1,"w":43,"h":65},
	"rotated": false,
	"trimmed": false,
	"spriteSourceSize": {"x":0,"y":0,"w":43,"h":65},
	"sourceSize": {"w":43,"h":65}
},
"Sparkle0001":
{
	"frame": {"x":1,"y":67,"w":43,"h":65},
	"rotated": false,
	"trimmed": false,
	"spriteSourceSize": {"x":0,"y":0,"w":43,"h":65},
	"sourceSize": {"w":43,"h":65}
},
"Sparkle0002":
{
	"frame": {"x":1,"y":133,"w":43,"h":65},
	"rotated": false,
	"trimmed": false,
	"spriteSourceSize": {"x":0,"y":0,"w":43,"h":65},
	"sourceSize": {"w":43,"h":65}
},
"Sparkle0003":
{
	"frame": {"x":1,"y":199,"w":43,"h":65},
	"rotated": false,
	"trimmed": false,
	"spriteSourceSize": {"x":0,"y":0,"w":43,"h":65},
	"sourceSize": {"w":43,"h":65}
},
"Sparkle0004":
{
	"frame": {"x":1,"y":265,"w":43,"h":65},
	"rotated": false,
	"trimmed": false,
	"spriteSourceSize": {"x":0,"y":0,"w":43,"h":65},
	"sourceSize": {"w":43,"h":65}
},
"Sparkle0005":
{
	"frame": {"x":1,"y":331,"w":43,"h":65},
	"rotated": false,
	"trimmed": false,
	"spriteSourceSize": {"x":0,"y":0,"w":43,"h":65},
	"sourceSize": {"w":43,"h":65}
},
"Sparkle0006":
{
	"frame": {"x":1,"y":397,"w":43,"h":65},
	"rotated": false,
	"trimmed": false,
	"spriteSourceSize": {"x":0,"y":0,"w":43,"h":65},
	"sourceSize": {"w":43,"h":65}
},
"Sparkle0007":
{
	"frame": {"x":45,"y":1,"w":43,"h":65},
	"rotated": false,
	"trimmed": false,
	"spriteSourceSize": {"x":0,"y":0,"w":43,"h":65},
	"sourceSize": {"w":43,"h":65}
},
"Sparkle0008":
{
	"frame": {"x":45,"y":67,"w":43,"h":65},
	"rotated": false,
	"trimmed": false,
	"spriteSourceSize": {"x":0,"y":0,"w":43,"h":65},
	"sourceSize": {"w":43,"h":65}
},
"Sparkle0009":
{
	"frame": {"x":45,"y":133,"w":43,"h":65},
	"rotated": false,
	"trimmed": false,
	"spriteSourceSize": {"x":0,"y":0,"w":43,"h":65},
	"sourceSize": {"w":43,"h":65}
},
"Sparkle0010":
{
	"frame": {"x":45,"y":199,"w":43,"h":65},
	"rotated": false,
	"trimmed": false,
	"spriteSourceSize": {"x":0,"y":0,"w":43,"h":65},
	"sourceSize": {"w":43,"h":65}
},
"Sparkle0011":
{
	"frame": {"x":45,"y":265,"w":43,"h":65},
	"rotated": false,
	"trimmed": false,
	"spriteSourceSize": {"x":0,"y":0,"w":43,"h":65},
	"sourceSize": {"w":43,"h":65}
},
"Sparkle0012":
{
	"frame": {"x":45,"y":331,"w":43,"h":65},
	"rotated": false,
	"trimmed": false,
	"spriteSourceSize": {"x":0,"y":0,"w":43,"h":65},
	"sourceSize": {"w":43,"h":65}
},
"Sparkle0013":
{
	"frame": {"x":45,"y":397,"w":43,"h":65},
	"rotated": false,
	"trimmed": false,
	"spriteSourceSize": {"x":0,"y":0,"w":43,"h":65},
	"sourceSize": {"w":43,"h":65}
},
"Sparkle0014":
{
	"frame": {"x":89,"y":1,"w":43,"h":65},
	"rotated": false,
	"trimmed": false,
	"spriteSourceSize": {"x":0,"y":0,"w":43,"h":65},
	"sourceSize": {"w":43,"h":65}
},
"Sparkle0015":
{
	"frame": {"x":89,"y":67,"w":43,"h":65},
	"rotated": false,
	"trimmed": false,
	"spriteSourceSize": {"x":0,"y":0,"w":43,"h":65},
	"sourceSize": {"w":43,"h":65}
},
"Sparkle0016":
{
	"frame": {"x":89,"y":133,"w":43,"h":65},
	"rotated": false,
	"trimmed": false,
	"spriteSourceSize": {"x":0,"y":0,"w":43,"h":65},
	"sourceSize": {"w":43,"h":65}
},
"Sparkle0017":
{
	"frame": {"x":89,"y":199,"w":43,"h":65},
	"rotated": false,
	"trimmed": false,
	"spriteSourceSize": {"x":0,"y":0,"w":43,"h":65},
	"sourceSize": {"w":43,"h":65}
},
"Sparkle0018":
{
	"frame": {"x":89,"y":265,"w":43,"h":65},
	"rotated": false,
	"trimmed": false,
	"spriteSourceSize": {"x":0,"y":0,"w":43,"h":65},
	"sourceSize": {"w":43,"h":65}
},
"Sparkle0019":
{
	"frame": {"x":89,"y":331,"w":43,"h":65},
	"rotated": false,
	"trimmed": false,
	"spriteSourceSize": {"x":0,"y":0,"w":43,"h":65},
	"sourceSize": {"w":43,"h":65}
},
"Sparkle0020":
{
	"frame": {"x":89,"y":397,"w":43,"h":65},
	"rotated": false,
	"trimmed": false,
	"spriteSourceSize": {"x":0,"y":0,"w":43,"h":65},
	"sourceSize": {"w":43,"h":65}
},
"Sparkle0021":
{
	"frame": {"x":133,"y":1,"w":43,"h":65},
	"rotated": false,
	"trimmed": false,
	"spriteSourceSize": {"x":0,"y":0,"w":43,"h":65},
	"sourceSize": {"w":43,"h":65}
},
"Sparkle0022":
{
	"frame": {"x":133,"y":67,"w":43,"h":65},
	"rotated": false,
	"trimmed": false,
	"spriteSourceSize": {"x":0,"y":0,"w":43,"h":65},
	"sourceSize": {"w":43,"h":65}
},
"Sparkle0023":
{
	"frame": {"x":133,"y":133,"w":43,"h":65},
	"rotated": false,
	"trimmed": false,
	"spriteSourceSize": {"x":0,"y":0,"w":43,"h":65},
	"sourceSize": {"w":43,"h":65}
},
"Sparkle0024":
{
	"frame": {"x":133,"y":199,"w":43,"h":65},
	"rotated": false,
	"trimmed": false,
	"spriteSourceSize": {"x":0,"y":0,"w":43,"h":65},
	"sourceSize": {"w":43,"h":65}
},
"Sparkle0025":
{
	"frame": {"x":133,"y":265,"w":43,"h":65},
	"rotated": false,
	"trimmed": false,
	"spriteSourceSize": {"x":0,"y":0,"w":43,"h":65},
	"sourceSize": {"w":43,"h":65}
},
"Sparkle0026":
{
	"frame": {"x":133,"y":331,"w":43,"h":65},
	"rotated": false,
	"trimmed": false,
	"spriteSourceSize": {"x":0,"y":0,"w":43,"h":65},
	"sourceSize": {"w":43,"h":65}
}}
}
